watershed_delineation/__init__.py
watershed_delineation/cli.py
watershed_delineation/core.py
watershed_delineation-0.1.3.dist-info/METADATA
watershed_delineation-0.1.3.dist-info/WHEEL
watershed_delineation-0.1.3.dist-info/entry_points.txt
watershed_delineation-0.1.3.dist-info/top_level.txt
watershed_delineation-0.1.3.dist-info/RECORD
