Metadata-Version: 2.4
Name: watershed-delineation
Version: 0.1.3
Summary: A Python package for delineating watersheds from a DEM and pour point.
Author-email: FYEC <f.yunusemre@gmail.com>
License: MIT
Project-URL: Homepage, https://github.com/fyec/watershed-delineation
Project-URL: Bug Tracker, https://github.com/fyec/watershed-delineation/issues
Keywords: hydrology,watershed,gis,geospatial,whitebox-tools
Classifier: Development Status :: 4 - Beta
Classifier: Intended Audience :: Science/Research
Classifier: Topic :: Scientific/Engineering :: GIS
Classifier: License :: OSI Approved :: MIT License
Classifier: Programming Language :: Python :: 3
Classifier: Programming Language :: Python :: 3.9
Classifier: Programming Language :: Python :: 3.10
Classifier: Programming Language :: Python :: 3.11
Requires-Python: >=3.9
Requires-Dist: geopandas
Requires-Dist: rasterio
Requires-Dist: whitebox
Requires-Dist: pyproj
Requires-Dist: numpy
Requires-Dist: shapely
